{"namedChunkGroups":{"polyfill":{"name":"polyfill","assets":[{"name":"webpack-runtime-4b75c13d267bab819c66.js","size":5026},{"name":"polyfill-c1f02514f474a0d7ce45.js","size":84307}],"filteredAssets":0,"assetsSize":89333,"filteredAuxiliaryAssets":2,"auxiliaryAssetsSize":225443},"app":{"name":"app","assets":[{"name":"webpack-runtime-4b75c13d267bab819c66.js","size":5026},{"name":"framework-7beca42a64ac2a9b8375.js","size":129909},{"name":"app-2631fd34278b7a965509.js","size":65369}],"filteredAssets":0,"assetsSize":200304,"filteredAuxiliaryAssets":3,"auxiliaryAssetsSize":647820},"component---src-pages-404-js":{"name":"component---src-pages-404-js","assets":[{"name":"component---src-pages-404-js-c26ae80319792449458f.js","size":794}],"filteredAssets":0,"assetsSize":794,"filteredAuxiliaryAssets":1,"auxiliaryAssetsSize":1864},"component---src-pages-index-js":{"name":"component---src-pages-index-js","assets":[{"name":"styles.29d6aa109e48995abdfc.css","size":22884},{"name":"719c3ace37c1767b03172b67a1d4131abe60db8c-7259596d4507b98d6560.js","size":24049},{"name":"component---src-pages-index-js-fef1bad25db5e1db3d34.js","size":43808}],"filteredAssets":0,"assetsSize":90741,"filteredAuxiliaryAssets":10,"auxiliaryAssetsSize":3059628},"component---src-pages-sub-js":{"name":"component---src-pages-sub-js","assets":[{"name":"styles.29d6aa109e48995abdfc.css","size":22884},{"name":"719c3ace37c1767b03172b67a1d4131abe60db8c-7259596d4507b98d6560.js","size":24049},{"name":"component---src-pages-sub-js-acef868174100431710c.js","size":588}],"filteredAssets":0,"assetsSize":47521,"filteredAuxiliaryAssets":6,"auxiliaryAssetsSize":2437401}},"assetsByChunkName":{"polyfill":["webpack-runtime-4b75c13d267bab819c66.js","polyfill-c1f02514f474a0d7ce45.js"],"app":["webpack-runtime-4b75c13d267bab819c66.js","framework-7beca42a64ac2a9b8375.js","app-2631fd34278b7a965509.js"],"component---src-pages-404-js":["component---src-pages-404-js-c26ae80319792449458f.js"],"component---src-pages-index-js":["styles.29d6aa109e48995abdfc.css","719c3ace37c1767b03172b67a1d4131abe60db8c-7259596d4507b98d6560.js","component---src-pages-index-js-fef1bad25db5e1db3d34.js"],"component---src-pages-sub-js":["styles.29d6aa109e48995abdfc.css","719c3ace37c1767b03172b67a1d4131abe60db8c-7259596d4507b98d6560.js","component---src-pages-sub-js-acef868174100431710c.js"]},"childAssetsByChunkName":{}}